circuit_maintenance_parser/__init__.py
circuit_maintenance_parser/cli.py
circuit_maintenance_parser/constants.py
circuit_maintenance_parser/data/worldcities.csv
circuit_maintenance_parser/data.py
circuit_maintenance_parser/errors.py
circuit_maintenance_parser/output.py
circuit_maintenance_parser/parser.py
circuit_maintenance_parser/parsers/__init__.py
circuit_maintenance_parser/parsers/apple.py
circuit_maintenance_parser/parsers/aquacomms.py
circuit_maintenance_parser/parsers/att.py
circuit_maintenance_parser/parsers/aws.py
circuit_maintenance_parser/parsers/bso.py
circuit_maintenance_parser/parsers/cogent.py
circuit_maintenance_parser/parsers/colt.py
circuit_maintenance_parser/parsers/crowncastle.py
circuit_maintenance_parser/parsers/equinix.py
circuit_maintenance_parser/parsers/globalcloudxchange.py
circuit_maintenance_parser/parsers/google.py
circuit_maintenance_parser/parsers/gtt.py
circuit_maintenance_parser/parsers/hgc.py
circuit_maintenance_parser/parsers/lumen.py
circuit_maintenance_parser/parsers/megaport.py
circuit_maintenance_parser/parsers/momentum.py
circuit_maintenance_parser/parsers/netflix.py
circuit_maintenance_parser/parsers/openai.py
circuit_maintenance_parser/parsers/pccw.py
circuit_maintenance_parser/parsers/seaborn.py
circuit_maintenance_parser/parsers/sparkle.py
circuit_maintenance_parser/parsers/tata.py
circuit_maintenance_parser/parsers/telstra.py
circuit_maintenance_parser/parsers/turkcell.py
circuit_maintenance_parser/parsers/verizon.py
circuit_maintenance_parser/parsers/windstream.py
circuit_maintenance_parser/parsers/zayo.py
circuit_maintenance_parser/processor.py
circuit_maintenance_parser/processors/__init__.py
circuit_maintenance_parser/provider.py
circuit_maintenance_parser/utils.py
circuit_maintenance_parser-2.9.0.dist-info/METADATA
circuit_maintenance_parser-2.9.0.dist-info/WHEEL
circuit_maintenance_parser-2.9.0.dist-info/entry_points.txt
circuit_maintenance_parser-2.9.0.dist-info/licenses/LICENSE
circuit_maintenance_parser-2.9.0.dist-info/RECORD
