Metadata-Version: 2.4
Name: circuit-maintenance-parser
Version: 2.9.0
Summary: Python library to parse Circuit Maintenance notifications and return a structured data back
License: Apache-2.0
License-File: LICENSE
Keywords: parser,circuit,maintenance
Author: Network to Code
Author-email: opensource@networktocode.com
Requires-Python: >=3.9,<4.0
Classifier: License :: OSI Approved :: Apache Software License
Classifier: Programming Language :: Python :: 3
Classifier: Programming Language :: Python :: 3.9
Classifier: Programming Language :: Python :: 3.10
Classifier: Programming Language :: Python :: 3.11
Classifier: Programming Language :: Python :: 3.12
Classifier: Programming Language :: Python :: 3.13
Classifier: Programming Language :: Python :: 3.14
Provides-Extra: openai
Provides-Extra: xlsx
Requires-Dist: backoff (>=1.11.1,<2.0.0)
Requires-Dist: bs4 (>=0.0.2,<0.0.3)
Requires-Dist: chardet (>=5,<6)
Requires-Dist: click (>=7.1,<9.0)
Requires-Dist: geopy (>=2.1.0,<3.0.0)
Requires-Dist: icalendar (>=5.0.0,<6.0.0)
Requires-Dist: lxml (>=4.6.2,<6)
Requires-Dist: openai (>=1.2.4) ; extra == "openai"
Requires-Dist: openpyxl (>=3.1.5,<4.0.0) ; extra == "xlsx"
Requires-Dist: pandas (>=2.2.3,<3.0.0) ; extra == "xlsx"
Requires-Dist: pydantic (>=1.10.4,<3)
Requires-Dist: python-dateutil (>=2.9.0,<3.0.0)
Requires-Dist: timezonefinder (>=6.0.1,<7.0.0)
Project-URL: Homepage, https://github.com/networktocode/circuit-maintenance-parser
Project-URL: Repository, https://github.com/networktocode/circuit-maintenance-parser
